elm_kernel/__init__.py
elm_kernel/__main__.py
elm_kernel/install.py
elm_kernel/kernel.py
elm_kernel-0.21.1.dist-info/LICENCE.txt
elm_kernel-0.21.1.dist-info/METADATA
elm_kernel-0.21.1.dist-info/WHEEL
elm_kernel-0.21.1.dist-info/top_level.txt
elm_kernel-0.21.1.dist-info/RECORD
