Metadata-Version: 2.1
Name: elm-kernel
Version: 0.21.1
Summary: Jupyter kernel for executing Elm code
Home-page: https://github.com/abingham/jupyter-elm-kernel
Author: Austin Bingham
Author-email: austin@sixty-north.com
License: UNKNOWN
Platform: UNKNOWN
Classifier: Intended Audience :: Developers
Classifier: License :: OSI Approved :: MIT License
Classifier: Programming Language :: Python :: 3
Requires-Dist: jupyter
